{
    "designJobs": [
        {
            "id": 1,
            "djId": "DJ-2024-0010",
            "projectId": 1,
            "jobTypeId": 1,
            "subject": "Banner Facebook: Happy New Year 2025",
            "priority": "normal",
            "status": "completed",
            "requesterId": 2,
            "requesterName": "สมหญิง Marketing",
            "assigneeId": 5,
            "createdAt": "2024-12-15T09:00:00Z",
            "submittedAt": "2024-12-15T10:00:00Z",
            "deadline": "2024-12-25T17:00:00Z",
            "completedAt": "2024-12-24T14:30:00Z",
            "slaWorkingDays": 7,
            "isOverdue": false,
            "overdueDays": 0,
            "brief": {
                "objective": "แบนเนอร์สวัสดีปีใหม่ 2568 สำหรับเพจโครงการ Sena Park",
                "headline": "Happy New Year 2025",
                "subHeadline": "เริ่มต้นปีใหม่กับบ้านคุณภาพจากเสนา",
                "sellingPoints": [
                    "ความสุขเริ่มต้นที่บ้าน"
                ],
                "price": null
            }
        },
        {
            "id": 2,
            "djId": "DJ-2024-0156",
            "projectId": 1,
            "jobTypeId": 1,
            "subject": "Ads Q1: โปรปลดล็อค LTV",
            "priority": "urgent",
            "status": "in_progress",
            "requesterId": 2,
            "requesterName": "สมหญิง Marketing",
            "assigneeId": 5,
            "createdAt": "2025-01-08T10:00:00Z",
            "submittedAt": "2025-01-08T10:15:00Z",
            "deadline": "2025-01-12T17:00:00Z",
            "slaWorkingDays": 3,
            "isOverdue": true,
            "overdueDays": 5,
            "brief": {
                "objective": "ทำ Artwork 5 ขนาด ยิง Ads Facebook เน้นมาตรการรัฐ LTV กู้ได้ 100%",
                "headline": "ปลดล็อค LTV กู้เต็ม 100%",
                "subHeadline": "ไม่ต้องดาวน์ เข้าอยู่ได้เลย",
                "sellingPoints": [
                    "ฟรีค่าโอน",
                    "ฟรีแอร์",
                    "ฟรีผ้าม่าน"
                ],
                "price": "เริ่ม 2.59 ลบ."
            }
        },
        {
            "id": 3,
            "djId": "DJ-2025-0001",
            "projectId": 2,
            "jobTypeId": 2,
            "subject": "Brochure: Grand Opening Phase 2",
            "priority": "normal",
            "status": "pending_approval",
            "requesterId": 3,
            "requesterName": "สมชาย Marketing",
            "currentApproverId": 4,
            "assigneeId": null,
            "createdAt": "2025-01-14T09:00:00Z",
            "submittedAt": "2025-01-14T09:30:00Z",
            "deadline": "2025-01-24T17:00:00Z",
            "slaWorkingDays": 10,
            "isOverdue": false,
            "overdueDays": 0,
            "brief": {
                "objective": "โบรชัวร์ A4 พับครึ่ง สำหรับงานเปิดเฟส 2",
                "headline": "Sena Ville: New Phase",
                "subHeadline": "บ้านเดี่ยวโซนหน้าสวน",
                "sellingPoints": [
                    "Smart Energy",
                    "Solar Roof 5kW",
                    "EV Charger"
                ],
                "price": "เริ่ม 8-12 ลบ."
            }
        },
        {
            "id": 4,
            "djId": "DJ-2025-0002",
            "projectId": 3,
            "jobTypeId": 3,
            "subject": "Reel: รีวิวบ้านตัวอย่าง Type A",
            "priority": "normal",
            "status": "assigned",
            "requesterId": 7,
            "requesterName": "ณัฐยา Marketing",
            "assigneeId": 10,
            "createdAt": "2025-01-10T11:00:00Z",
            "submittedAt": "2025-01-10T11:30:00Z",
            "deadline": "2025-01-20T17:00:00Z",
            "slaWorkingDays": 7,
            "isOverdue": false,
            "overdueDays": 0,
            "brief": {
                "objective": "คลิปสั้นแนวตั้ง (Reel/TikTok) เดินชมบ้านตัวอย่าง เน้น Solar Roof",
                "headline": "บ้านพลังงานทดแทน",
                "subHeadline": "ลดค่าไฟได้จริง เดือนละ 2,000+",
                "sellingPoints": [
                    "ประหยัดไฟ",
                    "ขายไฟคืนได้"
                ],
                "price": null
            }
        },
        {
            "id": 5,
            "djId": "DJ-2025-0003",
            "projectId": 4,
            "jobTypeId": 4,
            "subject": "Rich Menu: Valentine Promo",
            "priority": "low",
            "status": "draft",
            "requesterId": 2,
            "requesterName": "สมหญิง Marketing",
            "assigneeId": null,
            "createdAt": "2025-01-16T15:00:00Z",
            "submittedAt": null,
            "deadline": null,
            "slaWorkingDays": 5,
            "isOverdue": false,
            "overdueDays": 0,
            "brief": {
                "objective": "เปลี่ยนธีม LINE Rich Menu ต้อนรับวาเลนไทน์",
                "headline": "Love is All Around",
                "subHeadline": null,
                "sellingPoints": [],
                "price": null
            }
        },
        {
            "id": 6,
            "djId": "DJ-2025-0004",
            "projectId": 1,
            "jobTypeId": 5,
            "subject": "Landing Page: ลงทะเบียนรับสิทธิ์",
            "priority": "urgent",
            "status": "review",
            "requesterId": 11,
            "requesterName": "วราภรณ์ Marketing",
            "assigneeId": 6,
            "createdAt": "2025-01-05T08:00:00Z",
            "submittedAt": "2025-01-05T08:30:00Z",
            "deadline": "2025-01-12T17:00:00Z",
            "slaWorkingDays": 5,
            "isOverdue": true,
            "overdueDays": 5,
            "brief": {
                "objective": "หน้า Salepage สำหรับยิง Lead Facebook ลงทะเบียนจองสิทธิ์ Pre-sale",
                "headline": "Exclusive Pre-sale",
                "subHeadline": "ลงทะเบียนรับส่วนลดเพิ่ม 100,000",
                "sellingPoints": [
                    "ใกล้รถไฟฟ้า 200m",
                    "ส่วนกลาง 5 ไร่"
                ],
                "price": "เริ่ม 1.99 ลบ."
            }
        },
        {
            "id": 7,
            "djId": "DJ-2025-0005",
            "projectId": 2,
            "jobTypeId": 6,
            "subject": "Booth Design: งานมหกรรมบ้านฯ",
            "priority": "urgent",
            "status": "rejected",
            "requesterId": 3,
            "requesterName": "สมชาย Marketing",
            "currentApproverId": 4,
            "assigneeId": null,
            "createdAt": "2025-01-13T10:00:00Z",
            "submittedAt": "2025-01-13T10:30:00Z",
            "deadline": "2025-01-20T17:00:00Z",
            "slaWorkingDays": 5,
            "isOverdue": false,
            "overdueDays": 0,
            "brief": {
                "objective": "ออกแบบฉากหลังบูธ งานมหกรรมบ้านและคอนโด ศูนย์สิริกิติ์",
                "headline": "Sena Solar House",
                "subHeadline": null,
                "sellingPoints": [],
                "price": null
            },
            "rejectReason": "ข้อมูลขนาดบูธไม่ชัดเจน กรุณาแนบ Floor Plan ของงานมาด้วยครับ"
        },
        {
            "id": 8,
            "djId": "DJ-2025-0006",
            "projectId": 1,
            "jobTypeId": 1,
            "subject": "Social Content: How to กู้บ้าน",
            "priority": "normal",
            "status": "approved",
            "requesterId": 7,
            "requesterName": "ณัฐยา Marketing",
            "assigneeId": 5,
            "createdAt": "2025-01-15T09:00:00Z",
            "submittedAt": "2025-01-15T09:15:00Z",
            "deadline": "2025-01-22T17:00:00Z",
            "slaWorkingDays": 3,
            "isOverdue": false,
            "overdueDays": 0,
            "brief": {
                "objective": "ทำ Album Content 5 ภาพ ให้ความรู้เรื่องการเตรียมเอกสารกู้บ้าน",
                "headline": "กู้บ้านฉบับมนุษย์เงินเดือน",
                "subHeadline": "เตรียมตัวยังไงให้ผ่านฉลุย",
                "sellingPoints": [
                    "ไม่ต้องมีคนค้ำ",
                    "อายุงาน 6 เดือนกู้ได้"
                ],
                "price": null
            }
        },
        {
            "id": 9,
            "djId": "DJ-2025-0007",
            "projectId": 3,
            "jobTypeId": 2,
            "subject": "Direct Mail: จดหมายเชิญ VIP",
            "priority": "normal",
            "status": "pending_approval",
            "requesterId": 11,
            "requesterName": "วราภรณ์ Marketing",
            "currentApproverId": 8,
            "assigneeId": null,
            "createdAt": "2025-01-16T14:00:00Z",
            "submittedAt": "2025-01-16T14:30:00Z",
            "deadline": "2025-01-23T17:00:00Z",
            "slaWorkingDays": 5,
            "isOverdue": false,
            "overdueDays": 0,
            "brief": {
                "objective": "การ์ดเชิญลูกค้าเก่า แนะนำเพื่อนมาซื้อโครงการใหม่",
                "headline": "Member Get Member",
                "subHeadline": "แนะนำเพื่อนรับค่าแนะนำสูงสุด 50,000 บาท",
                "sellingPoints": [],
                "price": null
            }
        },
        {
            "id": 10,
            "djId": "DJ-2025-0008",
            "projectId": 4,
            "jobTypeId": 4,
            "subject": "Billboard: หน้าโครงการ (30x10m)",
            "priority": "urgent",
            "status": "in_progress",
            "requesterId": 2,
            "requesterName": "สมหญิง Marketing",
            "assigneeId": 9,
            "createdAt": "2025-01-02T10:00:00Z",
            "submittedAt": "2025-01-02T10:30:00Z",
            "deadline": "2025-01-20T17:00:00Z",
            "slaWorkingDays": 10,
            "isOverdue": false,
            "overdueDays": 0,
            "brief": {
                "objective": "เปลี่ยนไวนิลหน้าโครงการขนาดใหญ่",
                "headline": "Sena Kith Condo",
                "subHeadline": "คอนโดต่ำล้าน ผ่อนถูกกว่าเช่า",
                "sellingPoints": [
                    "ใกล้แหล่งงาน",
                    "เฟอร์ครบ",
                    "คุ้มกว่าเช่า"
                ],
                "price": "990,000.-"
            }
        },
        {
            "id": 11,
            "djId": "DJ-2025-0009",
            "projectId": 1,
            "jobTypeId": 1,
            "subject": "IG Story: รีวิวส่วนกลาง Live",
            "priority": "normal",
            "status": "completed",
            "requesterId": 7,
            "requesterName": "ณัฐยา Marketing",
            "assigneeId": 5,
            "createdAt": "2025-01-05T09:00:00Z",
            "submittedAt": "2025-01-05T09:30:00Z",
            "deadline": "2025-01-10T17:00:00Z",
            "completedAt": "2025-01-09T16:00:00Z",
            "slaWorkingDays": 3,
            "isOverdue": false,
            "overdueDays": 0,
            "brief": {
                "objective": "ภาพนิ่ง 3 ภาพ ลง Story IG เน้นสระว่ายน้ำและฟิตเนส",
                "headline": "Luxury Facilities",
                "subHeadline": "เปิดให้ชมแล้ววันนี้",
                "sellingPoints": [],
                "price": null
            }
        },
        {
            "id": 12,
            "djId": "DJ-2025-0010",
            "projectId": 2,
            "jobTypeId": 6,
            "subject": "Vinyl: ป้ายกองโจร (ทางลัด)",
            "priority": "normal",
            "status": "completed",
            "requesterId": 3,
            "requesterName": "สมชาย Marketing",
            "assigneeId": 9,
            "createdAt": "2024-12-28T09:00:00Z",
            "submittedAt": "2024-12-28T09:30:00Z",
            "deadline": "2025-01-05T17:00:00Z",
            "completedAt": "2025-01-04T11:00:00Z",
            "slaWorkingDays": 5,
            "isOverdue": false,
            "overdueDays": 0,
            "brief": {
                "objective": "ป้ายบอกทางเข้าโครงการ ขนาด 1.2x2.4m",
                "headline": "ตรงไป 500ม.",
                "subHeadline": "Sena Ville",
                "sellingPoints": [],
                "price": null
            }
        },
        {
            "id": 13,
            "djId": "DJ-2025-0011",
            "projectId": 3,
            "jobTypeId": 3,
            "subject": "VDO: สัมภาษณ์ลูกบ้าน",
            "priority": "normal",
            "status": "pending_approval",
            "requesterId": 2,
            "requesterName": "สมหญิง Marketing",
            "currentApproverId": 4,
            "assigneeId": null,
            "createdAt": "2025-01-15T11:00:00Z",
            "submittedAt": "2025-01-15T11:30:00Z",
            "deadline": "2025-01-30T17:00:00Z",
            "slaWorkingDays": 10,
            "isOverdue": false,
            "overdueDays": 0,
            "brief": {
                "objective": "ตัดต่อบทสัมภาษณ์ความประทับใจลูกบ้านที่เข้าอยู่จริง",
                "headline": "Real Voice, Real Home",
                "subHeadline": "ทำไมถึงเลือกเสนา?",
                "sellingPoints": [
                    "บริการหลังการขาย",
                    "นิติบุคคลเข้มแข็ง"
                ],
                "price": null
            }
        },
        {
            "id": 14,
            "djId": "DJ-2025-0012",
            "projectId": 1,
            "jobTypeId": 5,
            "subject": "Website Banner: Main Carousel",
            "priority": "normal",
            "status": "draft",
            "requesterId": 2,
            "requesterName": "สมหญิง Marketing",
            "assigneeId": null,
            "createdAt": "2025-01-17T09:00:00Z",
            "submittedAt": null,
            "deadline": null,
            "slaWorkingDays": 2,
            "isOverdue": false,
            "overdueDays": 0,
            "brief": {
                "objective": "เปลี่ยนภาพสไลด์หน้าแรกเว็บไซต์บริษัท",
                "headline": "Sena Solar House",
                "subHeadline": "บ้านติดโซลาร์ ประหยัดไฟ 25 ปี",
                "sellingPoints": [],
                "price": null
            }
        },
        {
            "id": 15,
            "djId": "DJ-2025-0013",
            "projectId": 4,
            "jobTypeId": 1,
            "subject": "GDN Banners: Remarketing",
            "priority": "normal",
            "status": "review",
            "requesterId": 11,
            "requesterName": "วราภรณ์ Marketing",
            "assigneeId": 5,
            "createdAt": "2025-01-10T13:00:00Z",
            "submittedAt": "2025-01-10T13:30:00Z",
            "deadline": "2025-01-18T17:00:00Z",
            "slaWorkingDays": 5,
            "isOverdue": false,
            "overdueDays": 0,
            "brief": {
                "objective": "Google Display Network 8 ขนาด ตามลูกค้าที่เข้าเว็บ",
                "headline": "อย่าเพิ่งปิด!",
                "subHeadline": "โปรลับเฉพาะคุณ ลดเพิ่ม 20,000",
                "sellingPoints": [],
                "price": null
            }
        },
        {
            "id": 16,
            "djId": "DJ-2025-0014",
            "projectId": 2,
            "jobTypeId": 4,
            "subject": "J-Flag: หน้าสำนักงานขาย",
            "priority": "urgent",
            "status": "assigned",
            "requesterId": 3,
            "requesterName": "สมชาย Marketing",
            "assigneeId": 9,
            "createdAt": "2025-01-16T08:00:00Z",
            "submittedAt": "2025-01-16T08:30:00Z",
            "deadline": "2025-01-19T17:00:00Z",
            "slaWorkingDays": 3,
            "isOverdue": false,
            "overdueDays": 0,
            "brief": {
                "objective": "ธงญี่ปุ่น 4 จุด หน้าทางเข้าโครงการ",
                "headline": "Open House",
                "subHeadline": "18-19 ม.ค. นี้",
                "sellingPoints": [
                    "แจกทอง",
                    "iPhone 15"
                ],
                "price": null
            }
        },
        {
            "id": 17,
            "djId": "DJ-2025-0015",
            "projectId": 1,
            "jobTypeId": 1,
            "subject": "FB Post: แจ้งซ่อมบำรุง",
            "priority": "normal",
            "status": "closed",
            "requesterId": 2,
            "requesterName": "สมหญิง Marketing",
            "assigneeId": 5,
            "createdAt": "2024-11-20T10:00:00Z",
            "submittedAt": "2024-11-20T10:30:00Z",
            "deadline": "2024-11-23T17:00:00Z",
            "completedAt": "2024-11-22T14:00:00Z",
            "slaWorkingDays": 2,
            "isOverdue": false,
            "overdueDays": 0,
            "brief": {
                "objective": "ภาพแจ้งลูกบ้านเรื่องปิดปรับปรุงสระว่ายน้ำชั่วคราว",
                "headline": "Maintenance Notice",
                "subHeadline": "ขออภัยในความไม่สะดวก",
                "sellingPoints": [],
                "price": null
            }
        },
        {
            "id": 18,
            "djId": "DJ-2025-0016",
            "projectId": 3,
            "jobTypeId": 6,
            "subject": "Roll-up: งาน Bank Event",
            "priority": "urgent",
            "status": "pending_approval",
            "requesterId": 7,
            "requesterName": "ณัฐยา Marketing",
            "currentApproverId": 8,
            "assigneeId": null,
            "createdAt": "2025-01-17T09:30:00Z",
            "submittedAt": "2025-01-17T10:00:00Z",
            "deadline": "2025-01-20T17:00:00Z",
            "slaWorkingDays": 3,
            "isOverdue": false,
            "overdueDays": 0,
            "brief": {
                "objective": "Roll-up 85x200cm สำหรับตั้งบูธที่ KBank สำนักงานใหญ่",
                "headline": "Sena x KBank",
                "subHeadline": "โปรฯ กบข. ดอกเบี้ยพิเศษ",
                "sellingPoints": [
                    "กู้ได้ 110%",
                    "ผ่อนล้านละ 3,000"
                ],
                "price": null
            }
        },
        {
            "id": 19,
            "djId": "DJ-2025-0017",
            "projectId": 4,
            "jobTypeId": 1,
            "subject": "Tiktok Cover Template",
            "priority": "normal",
            "status": "in_progress",
            "requesterId": 11,
            "requesterName": "วราภรณ์ Marketing",
            "assigneeId": 5,
            "createdAt": "2025-01-14T13:00:00Z",
            "submittedAt": "2025-01-14T13:30:00Z",
            "deadline": "2025-01-17T17:00:00Z",
            "slaWorkingDays": 3,
            "isOverdue": true,
            "overdueDays": 0,
            "brief": {
                "objective": "ทำเทมเพลตปกคลิป Tiktok ให้คุมโทนเดียวกัน",
                "headline": "Sena KPI Knowledge",
                "subHeadline": null,
                "sellingPoints": [],
                "price": null
            }
        },
        {
            "id": 20,
            "djId": "DJ-2025-0018",
            "projectId": 1,
            "jobTypeId": 3,
            "subject": "Animation: การทำงานของ Solar",
            "priority": "normal",
            "status": "assigned",
            "requesterId": 2,
            "requesterName": "สมหญิง Marketing",
            "assigneeId": 10,
            "createdAt": "2025-01-10T09:00:00Z",
            "submittedAt": "2025-01-10T09:30:00Z",
            "deadline": "2025-01-30T17:00:00Z",
            "slaWorkingDays": 15,
            "isOverdue": false,
            "overdueDays": 0,
            "brief": {
                "objective": "Motion Graphic อธิบายการทำงานของแผงโซลาร์เซลล์ แบบเข้าใจง่าย",
                "headline": "Solar 101",
                "subHeadline": "กลางวันใช้ไฟฟรี กลางคืนขายไฟคืน",
                "sellingPoints": [],
                "price": null
            }
        },
        {
            "id": 21,
            "djId": "DJ-2025-0019",
            "projectId": 2,
            "jobTypeId": 2,
            "subject": "Floor Plan: Redraw (3 Types)",
            "priority": "normal",
            "status": "approved",
            "requesterId": 3,
            "requesterName": "สมชาย Marketing",
            "assigneeId": null,
            "createdAt": "2025-01-16T15:30:00Z",
            "submittedAt": "2025-01-16T16:00:00Z",
            "deadline": "2025-01-23T17:00:00Z",
            "slaWorkingDays": 5,
            "isOverdue": false,
            "overdueDays": 0,
            "brief": {
                "objective": "ดราฟต์ผังห้องชุดใหม่ 3 แบบ (1 Bed, 1 Bed Plus, 2 Bed)",
                "headline": "New Unit Plan",
                "subHeadline": "ปรับฟังก์ชันใหม่ กว้างกว่าเดิม",
                "sellingPoints": [],
                "price": null
            }
        },
        {
            "id": 22,
            "djId": "DJ-2025-0020",
            "projectId": 3,
            "jobTypeId": 1,
            "subject": "LINE OA: Greeting Message",
            "priority": "low",
            "status": "completed",
            "requesterId": 7,
            "requesterName": "ณัฐยา Marketing",
            "assigneeId": 5,
            "createdAt": "2024-12-20T10:00:00Z",
            "submittedAt": "2024-12-20T10:30:00Z",
            "deadline": "2024-12-23T17:00:00Z",
            "completedAt": "2024-12-22T15:00:00Z",
            "slaWorkingDays": 3,
            "isOverdue": false,
            "overdueDays": 0,
            "brief": {
                "objective": "ภาพทักทายอัตโนมัติเมื่อลูกค้าแอดไลน์มาใหม่",
                "headline": "Welcome to Sena Club",
                "subHeadline": "กดลงทะเบียนเพื่อรับข่าวสาร",
                "sellingPoints": [],
                "price": null
            }
        },
        {
            "id": 23,
            "djId": "DJ-2025-0021",
            "projectId": 4,
            "jobTypeId": 5,
            "subject": "Website: Popup Banner",
            "priority": "urgent",
            "status": "review",
            "requesterId": 11,
            "requesterName": "วราภรณ์ Marketing",
            "assigneeId": 6,
            "createdAt": "2025-01-15T08:00:00Z",
            "submittedAt": "2025-01-15T08:30:00Z",
            "deadline": "2025-01-17T17:00:00Z",
            "slaWorkingDays": 2,
            "isOverdue": true,
            "overdueDays": 0,
            "brief": {
                "objective": "Popup หน้าเว็บ แจ้งโปรโมชั่น Last Minute Delay",
                "headline": "3 วันสุดท้าย!",
                "subHeadline": "ก่อนปรับราคาใหม่",
                "sellingPoints": [],
                "price": null
            }
        },
        {
            "id": 24,
            "djId": "DJ-2025-0022",
            "projectId": 1,
            "jobTypeId": 4,
            "subject": "Mockup: ของที่ระลึก (ร่ม/แก้ว)",
            "priority": "normal",
            "status": "pending_approval",
            "requesterId": 2,
            "requesterName": "สมหญิง Marketing",
            "currentApproverId": 4,
            "assigneeId": null,
            "createdAt": "2025-01-17T11:00:00Z",
            "submittedAt": "2025-01-17T11:30:00Z",
            "deadline": "2025-01-24T17:00:00Z",
            "slaWorkingDays": 5,
            "isOverdue": false,
            "overdueDays": 0,
            "brief": {
                "objective": "ออกแบบลายสกรีนลงบนร่มพับและแก้วเก็บความเย็น",
                "headline": "Premium Gift Set 2025",
                "subHeadline": null,
                "sellingPoints": [],
                "price": null
            }
        },
        {
            "id": 25,
            "djId": "DJ-2025-0023",
            "projectId": 2,
            "jobTypeId": 1,
            "subject": "FB Cover: เปลี่ยนธีมฤดูร้อน",
            "priority": "low",
            "status": "draft",
            "requesterId": 3,
            "requesterName": "สมชาย Marketing",
            "assigneeId": null,
            "createdAt": "2025-01-17T13:00:00Z",
            "submittedAt": null,
            "deadline": null,
            "slaWorkingDays": 3,
            "isOverdue": false,
            "overdueDays": 0,
            "brief": {
                "objective": "เตรียมรูปปกเพจสำหรับเดือนมีนาคม-เมษายน",
                "headline": "Summer Hot Deal",
                "subHeadline": "ร้อนนี้มีหนาว ลดเดือดทะลุปรอท",
                "sellingPoints": [],
                "price": null
            }
        }
    ]
}